{
 "packs": [
  {
   "id": "fr-b2-precise",
   "title": "B2 : le mot précis",
   "level": "B2",
   "sources": [
    "lexique383"
   ],
   "words": [
    {
     "id": "réticence",
     "hr": "réticence",
     "en": "reluctance, reticence",
     "pos": "n. f.",
     "example": {
      "target": "Il a accepté, non sans une certaine réticence.",
      "gloss": "He accepted, though not without some reluctance."
     }
    },
    {
     "id": "appréhension",
     "hr": "appréhension",
     "en": "apprehension, dread",
     "pos": "n. f.",
     "example": {
      "target": "Elle attend les résultats avec une réelle appréhension.",
      "gloss": "She awaits the results with real apprehension."
     }
    },
    {
     "id": "effroi",
     "hr": "effroi",
     "en": "terror, dread",
     "pos": "n. m.",
     "example": {
      "target": "La scène plongea les spectateurs dans l'effroi.",
      "gloss": "The scene plunged the onlookers into terror."
     }
    },
    {
     "id": "frayeur",
     "hr": "frayeur",
     "en": "fright",
     "pos": "n. f.",
     "example": {
      "target": "Il en fut quitte pour une belle frayeur.",
      "gloss": "He got off with a bad scare."
     }
    },
    {
     "id": "hantise",
     "hr": "hantise",
     "en": "obsessive fear, dread",
     "pos": "n. f.",
     "example": {
      "target": "La hantise de manquer le pousse à tout accumuler.",
      "gloss": "The dread of running short drives him to hoard everything."
     }
    },
    {
     "id": "allégresse",
     "hr": "allégresse",
     "en": "elation, joy",
     "pos": "n. f.",
     "example": {
      "target": "La nouvelle fut accueillie dans l'allégresse générale.",
      "gloss": "The news was greeted with general elation."
     }
    },
    {
     "id": "liesse",
     "hr": "liesse",
     "en": "jubilation",
     "pos": "n. f.",
     "example": {
      "target": "La foule en liesse a envahi les rues.",
      "gloss": "The jubilant crowd flooded the streets."
     }
    },
    {
     "id": "jubilation",
     "hr": "jubilation",
     "en": "jubilation, glee",
     "pos": "n. f.",
     "example": {
      "target": "Il annonça sa victoire avec une jubilation à peine contenue.",
      "gloss": "He announced his victory with barely contained glee."
     }
    },
    {
     "id": "quiétude",
     "hr": "quiétude",
     "en": "peace of mind, calm",
     "pos": "n. f.",
     "example": {
      "target": "Il goûtait la quiétude de ses matinées.",
      "gloss": "He savoured the calm of his mornings."
     }
    },
    {
     "id": "désarroi",
     "hr": "désarroi",
     "en": "confusion, dismay",
     "pos": "n. f.",
     "note": "n. m.",
     "example": {
      "target": "Face à l'imprévu, il laissa paraître son désarroi.",
      "gloss": "Faced with the unexpected, he let his dismay show."
     }
    },
    {
     "id": "accablement",
     "hr": "accablement",
     "en": "despondency, dejection",
     "pos": "n. m.",
     "example": {
      "target": "Un profond accablement se lisait sur son visage.",
      "gloss": "A deep dejection could be read on his face."
     }
    },
    {
     "id": "affliction",
     "hr": "affliction",
     "en": "affliction, grief",
     "pos": "n. f.",
     "example": {
      "target": "Elle traversa cette épreuve sans laisser voir son affliction.",
      "gloss": "She weathered the ordeal without showing her grief."
     }
    },
    {
     "id": "courroux",
     "hr": "courroux",
     "en": "wrath, anger",
     "pos": "n. m.",
     "example": {
      "target": "Sa remarque déchaîna le courroux de l'assemblée.",
      "gloss": "His remark unleashed the assembly's wrath."
     }
    },
    {
     "id": "exaspération",
     "hr": "exaspération",
     "en": "exasperation",
     "pos": "n. f.",
     "example": {
      "target": "Les retards répétés ont fini par susciter l'exaspération.",
      "gloss": "The repeated delays finally provoked exasperation."
     }
    },
    {
     "id": "ressentiment",
     "hr": "ressentiment",
     "en": "resentment",
     "pos": "n. m.",
     "example": {
      "target": "Il nourrit un vieux ressentiment contre ses anciens associés.",
      "gloss": "He harbours an old resentment against his former partners."
     }
    },
    {
     "id": "rancœur",
     "hr": "rancœur",
     "en": "rancour, bitterness",
     "pos": "n. f.",
     "example": {
      "target": "Des années après, la rancœur n'était toujours pas éteinte.",
      "gloss": "Years later, the rancour had still not died down."
     }
    },
    {
     "id": "animosité",
     "hr": "animosité",
     "en": "animosity",
     "pos": "n. f.",
     "example": {
      "target": "Le débat s'est tenu sans la moindre animosité.",
      "gloss": "The debate took place without the slightest animosity."
     }
    },
    {
     "id": "aversion",
     "hr": "aversion",
     "en": "aversion",
     "pos": "n. f.",
     "note": "aversion pour",
     "example": {
      "target": "Il éprouve une aversion marquée pour la mondanité.",
      "gloss": "He feels a marked aversion to social affairs."
     }
    },
    {
     "id": "répugnance",
     "hr": "répugnance",
     "en": "repugnance, reluctance",
     "pos": "n. f.",
     "example": {
      "target": "C'est avec répugnance qu'il s'est plié à cette exigence.",
      "gloss": "It was with reluctance that he yielded to this demand."
     }
    },
    {
     "id": "convoitise",
     "hr": "convoitise",
     "en": "covetousness, greed",
     "pos": "n. f.",
     "example": {
      "target": "Ces terres fertiles attisent bien des convoitises.",
      "gloss": "These fertile lands arouse much covetousness."
     }
    },
    {
     "id": "avidité",
     "hr": "avidité",
     "en": "avidity, greed",
     "pos": "n. f.",
     "example": {
      "target": "Il dévorait les livres avec une avidité sans fin.",
      "gloss": "He devoured books with endless avidity."
     }
    },
    {
     "id": "cupidité",
     "hr": "cupidité",
     "en": "cupidity, greed for money",
     "pos": "n. f.",
     "example": {
      "target": "Sa cupidité a fini par causer sa perte.",
      "gloss": "His greed for money eventually caused his downfall."
     }
    },
    {
     "id": "vanité",
     "hr": "vanité",
     "en": "vanity, conceit",
     "pos": "n. f.",
     "example": {
      "target": "Sa vanité l'aveugle sur ses propres limites.",
      "gloss": "His vanity blinds him to his own limits."
     }
    },
    {
     "id": "suffisance",
     "hr": "suffisance",
     "en": "self-importance, smugness",
     "pos": "n. f.",
     "example": {
      "target": "Il parle de tout avec une insupportable suffisance.",
      "gloss": "He speaks of everything with insufferable smugness."
     }
    },
    {
     "id": "arrogance",
     "hr": "arrogance",
     "en": "arrogance",
     "pos": "n. f.",
     "example": {
      "target": "Son arrogance lui a aliéné bien des soutiens.",
      "gloss": "His arrogance cost him many supporters."
     }
    },
    {
     "id": "condescendance",
     "hr": "condescendance",
     "en": "condescension",
     "pos": "n. f.",
     "example": {
      "target": "Il traite ses adversaires avec une froide condescendance.",
      "gloss": "He treats his opponents with cold condescension."
     }
    },
    {
     "id": "humilité",
     "hr": "humilité",
     "en": "humility",
     "pos": "n. f.",
     "example": {
      "target": "Le vrai savant garde toujours une part d'humilité.",
      "gloss": "The true scholar always retains a measure of humility."
     }
    },
    {
     "id": "déférence",
     "hr": "déférence",
     "en": "deference",
     "pos": "n. f.",
     "example": {
      "target": "Il s'adressa au maître avec une déférence marquée.",
      "gloss": "He addressed the master with marked deference."
     }
    },
    {
     "id": "désinvolture",
     "hr": "désinvolture",
     "en": "casualness, offhandedness",
     "pos": "n. f.",
     "example": {
      "target": "Il a répondu avec une désinvolture qui a choqué.",
      "gloss": "He replied with an offhandedness that shocked people."
     }
    },
    {
     "id": "nonchalance",
     "hr": "nonchalance",
     "en": "nonchalance",
     "pos": "n. f.",
     "example": {
      "target": "Sa nonchalance apparente cache un travail acharné.",
      "gloss": "His apparent nonchalance hides relentless work."
     }
    },
    {
     "id": "insouciance",
     "hr": "insouciance",
     "en": "carefreeness",
     "pos": "n. f.",
     "example": {
      "target": "Il regrette l'insouciance de ses jeunes années.",
      "gloss": "He misses the carefreeness of his younger years."
     }
    },
    {
     "id": "apathie",
     "hr": "apathie",
     "en": "apathy",
     "pos": "n. f.",
     "example": {
      "target": "L'apathie générale a laissé le champ libre aux extrêmes.",
      "gloss": "General apathy left the field clear for the extremes."
     }
    },
    {
     "id": "torpeur",
     "hr": "torpeur",
     "en": "torpor, lethargy",
     "pos": "n. f.",
     "example": {
      "target": "La chaleur plongeait la ville dans une torpeur épaisse.",
      "gloss": "The heat plunged the city into a thick torpor."
     }
    },
    {
     "id": "fébrilité",
     "hr": "fébrilité",
     "en": "feverishness, jitteriness",
     "pos": "n. f.",
     "example": {
      "target": "On sentait une certaine fébrilité à l'approche du vote.",
      "gloss": "A certain jitteriness was palpable as the vote drew near."
     }
    },
    {
     "id": "ferveur",
     "hr": "ferveur",
     "en": "fervour",
     "pos": "n. f.",
     "example": {
      "target": "Il défend ses idées avec une ferveur communicative.",
      "gloss": "He defends his ideas with an infectious fervour."
     }
    },
    {
     "id": "ardeur",
     "hr": "ardeur",
     "en": "ardour, zeal",
     "pos": "n. f.",
     "example": {
      "target": "Il se remit au travail avec une ardeur redoublée.",
      "gloss": "He got back to work with redoubled zeal."
     }
    },
    {
     "id": "fougue",
     "hr": "fougue",
     "en": "fire, impetuosity",
     "pos": "n. f.",
     "example": {
      "target": "La fougue de la jeunesse tempère mal sa prudence.",
      "gloss": "The fire of youth sits ill with his caution."
     }
    },
    {
     "id": "véhémence",
     "hr": "véhémence",
     "en": "vehemence",
     "pos": "n. f.",
     "example": {
      "target": "Il a protesté avec une véhémence inattendue.",
      "gloss": "He protested with unexpected vehemence."
     }
    },
    {
     "id": "virulence",
     "hr": "virulence",
     "en": "virulence, harshness",
     "pos": "n. f.",
     "example": {
      "target": "La virulence de la critique a surpris jusqu'à ses amis.",
      "gloss": "The harshness of the criticism surprised even his friends."
     }
    },
    {
     "id": "intransigeance",
     "hr": "intransigeance",
     "en": "intransigence",
     "pos": "n. f.",
     "example": {
      "target": "Son intransigeance a fait échouer toute négociation.",
      "gloss": "His intransigence wrecked every negotiation."
     }
    },
    {
     "id": "fermeté",
     "hr": "fermeté",
     "en": "firmness, resolve",
     "pos": "n. f.",
     "example": {
      "target": "Il a maintenu sa position avec une fermeté tranquille.",
      "gloss": "He held his position with quiet firmness."
     }
    },
    {
     "id": "ténacité",
     "hr": "ténacité",
     "en": "tenacity",
     "pos": "n. f.",
     "example": {
      "target": "Sa ténacité a fini par payer.",
      "gloss": "His tenacity eventually paid off."
     }
    },
    {
     "id": "opiniâtreté",
     "hr": "opiniâtreté",
     "en": "doggedness, stubbornness",
     "pos": "n. f.",
     "example": {
      "target": "Il poursuit son but avec une opiniâtreté rare.",
      "gloss": "He pursues his goal with rare doggedness."
     }
    },
    {
     "id": "obstination",
     "hr": "obstination",
     "en": "obstinacy",
     "pos": "n. f.",
     "example": {
      "target": "Son obstination confine parfois à l'aveuglement.",
      "gloss": "His obstinacy sometimes borders on blindness."
     }
    },
    {
     "id": "entêtement",
     "hr": "entêtement",
     "en": "stubbornness",
     "pos": "n. m.",
     "example": {
      "target": "Par pur entêtement, il refuse d'admettre son erreur.",
      "gloss": "Out of sheer stubbornness, he refuses to admit his mistake."
     }
    },
    {
     "id": "détermination",
     "hr": "détermination",
     "en": "determination",
     "pos": "n. f.",
     "example": {
      "target": "Elle a annoncé sa décision avec une froide détermination.",
      "gloss": "She announced her decision with cold determination."
     }
    },
    {
     "id": "abnégation",
     "hr": "abnégation",
     "en": "self-sacrifice, abnegation",
     "pos": "n. f.",
     "example": {
      "target": "Il s'est dévoué à cette cause avec une totale abnégation.",
      "gloss": "He devoted himself to this cause with total self-sacrifice."
     }
    },
    {
     "id": "altruisme",
     "hr": "altruisme",
     "en": "altruism",
     "pos": "n. m.",
     "example": {
      "target": "Son altruisme n'attendait ni éloge ni récompense.",
      "gloss": "His altruism sought neither praise nor reward."
     }
    },
    {
     "id": "malveillance",
     "hr": "malveillance",
     "en": "malice, ill will",
     "pos": "n. f.",
     "example": {
      "target": "Rien, dans son geste, ne trahissait la moindre malveillance.",
      "gloss": "Nothing in his gesture betrayed the slightest ill will."
     }
    },
    {
     "id": "duplicité",
     "hr": "duplicité",
     "en": "duplicity",
     "pos": "n. f.",
     "example": {
      "target": "Sa duplicité a fini par éclater au grand jour.",
      "gloss": "His duplicity finally came to light."
     }
    },
    {
     "id": "hypocrisie",
     "hr": "hypocrisie",
     "en": "hypocrisy",
     "pos": "n. f.",
     "example": {
      "target": "Cette indignation soudaine sent l'hypocrisie.",
      "gloss": "This sudden indignation smacks of hypocrisy."
     }
    },
    {
     "id": "probité",
     "hr": "probité",
     "en": "probity, integrity",
     "pos": "n. f.",
     "example": {
      "target": "Nul ne met en doute la probité du magistrat.",
      "gloss": "No one doubts the magistrate's integrity."
     }
    },
    {
     "id": "droiture",
     "hr": "droiture",
     "en": "uprightness, rectitude",
     "pos": "n. f.",
     "example": {
      "target": "On loue en lui une droiture sans faille.",
      "gloss": "He is praised for an unfailing uprightness."
     }
    },
    {
     "id": "loyauté",
     "hr": "loyauté",
     "en": "loyalty",
     "pos": "n. f.",
     "example": {
      "target": "Il a servi la maison avec une loyauté exemplaire.",
      "gloss": "He served the firm with exemplary loyalty."
     }
    },
    {
     "id": "sollicitude",
     "hr": "sollicitude",
     "en": "solicitude, care",
     "pos": "n. f.",
     "example": {
      "target": "Elle entoure ses proches d'une sollicitude constante.",
      "gloss": "She surrounds her loved ones with constant care."
     }
    },
    {
     "id": "mansuétude",
     "hr": "mansuétude",
     "en": "leniency, forbearance",
     "pos": "n. f.",
     "example": {
      "target": "Le juge a fait preuve d'une rare mansuétude.",
      "gloss": "The judge showed rare leniency."
     }
    },
    {
     "id": "clémence",
     "hr": "clémence",
     "en": "clemency, mercy",
     "pos": "n. f.",
     "example": {
      "target": "Les avocats ont plaidé la clémence.",
      "gloss": "The lawyers pleaded for clemency."
     }
    },
    {
     "id": "indulgence",
     "hr": "indulgence",
     "en": "indulgence, leniency",
     "pos": "n. f.",
     "example": {
      "target": "Il juge les autres avec bien moins d'indulgence que lui-même.",
      "gloss": "He judges others with far less leniency than himself."
     }
    },
    {
     "id": "vestige",
     "hr": "vestige",
     "en": "vestige, remnant",
     "pos": "n. m.",
     "example": {
      "target": "Ce mur est le dernier vestige de l'ancien château.",
      "gloss": "This wall is the last remnant of the old castle."
     }
    },
    {
     "id": "réminiscence",
     "hr": "réminiscence",
     "en": "reminiscence, echo",
     "pos": "n. f.",
     "example": {
      "target": "On perçoit dans ce tableau des réminiscences classiques.",
      "gloss": "One perceives classical echoes in this painting."
     }
    },
    {
     "id": "stigmate",
     "hr": "stigmate",
     "en": "mark, stigma",
     "pos": "n. m.",
     "example": {
      "target": "La ville porte encore les stigmates de la guerre.",
      "gloss": "The city still bears the scars of the war."
     }
    },
    {
     "id": "apogée",
     "hr": "apogée",
     "en": "peak, apogee",
     "pos": "n. m.",
     "example": {
      "target": "L'artiste était alors à l'apogée de sa gloire.",
      "gloss": "The artist was then at the peak of his fame."
     }
    },
    {
     "id": "paroxysme",
     "hr": "paroxysme",
     "en": "climax, peak",
     "pos": "n. m.",
     "example": {
      "target": "La tension atteignit son paroxysme au dernier acte.",
      "gloss": "The tension reached its climax in the final act."
     }
    },
    {
     "id": "comble",
     "hr": "comble",
     "en": "height, peak",
     "pos": "n. m.",
     "example": {
      "target": "C'est le comble de l'ironie que de l'accuser, lui.",
      "gloss": "It is the height of irony to accuse him, of all people."
     }
    },
    {
     "id": "décadence",
     "hr": "décadence",
     "en": "decadence, decay",
     "pos": "n. f.",
     "example": {
      "target": "Les moralistes voyaient partout des signes de décadence.",
      "gloss": "Moralists saw signs of decadence everywhere."
     }
    },
    {
     "id": "déchéance",
     "hr": "déchéance",
     "en": "downfall, degradation",
     "pos": "n. f.",
     "example": {
      "target": "Le roman retrace la lente déchéance du personnage.",
      "gloss": "The novel traces the character's slow downfall."
     }
    },
    {
     "id": "avènement",
     "hr": "avènement",
     "en": "advent, coming",
     "pos": "n. m.",
     "example": {
      "target": "L'avènement de l'imprimerie a bouleversé le savoir.",
      "gloss": "The advent of printing transformed knowledge."
     }
    },
    {
     "id": "colossal",
     "hr": "colossal",
     "en": "colossal",
     "pos": "adj.",
     "note": "f. colossale",
     "example": {
      "target": "Le chantier a nécessité un effort colossal.",
      "gloss": "The project required a colossal effort."
     }
    },
    {
     "id": "démesuré",
     "hr": "démesuré",
     "en": "excessive, immoderate",
     "pos": "adj.",
     "example": {
      "target": "Son ambition démesurée l'a mené à sa perte.",
      "gloss": "His immoderate ambition led to his downfall."
     }
    },
    {
     "id": "exigu",
     "hr": "exigu",
     "en": "cramped, tiny",
     "pos": "adj.",
     "note": "f. exiguë",
     "example": {
      "target": "Ils s'entassaient dans un logement exigu.",
      "gloss": "They were crammed into a cramped dwelling."
     }
    },
    {
     "id": "infime",
     "hr": "infime",
     "en": "minuscule, tiny",
     "pos": "adj.",
     "example": {
      "target": "La différence est infime, presque imperceptible.",
      "gloss": "The difference is minuscule, almost imperceptible."
     }
    },
    {
     "id": "modique",
     "hr": "modique",
     "en": "modest, small (sum)",
     "pos": "adj.",
     "example": {
      "target": "Il a acquis le tableau pour une somme modique.",
      "gloss": "He acquired the painting for a modest sum."
     }
    },
    {
     "id": "appréciable",
     "hr": "appréciable",
     "en": "appreciable, sizeable",
     "pos": "adj.",
     "example": {
      "target": "Le gain de temps est tout à fait appréciable.",
      "gloss": "The time saved is quite appreciable."
     }
    },
    {
     "id": "conséquent",
     "hr": "conséquent",
     "en": "sizeable, substantial",
     "pos": "adj.",
     "note": "faux ami : pas 'consequent'",
     "example": {
      "target": "L'opération a exigé un budget conséquent.",
      "gloss": "The operation required a sizeable budget."
     }
    },
    {
     "id": "éminent",
     "hr": "éminent",
     "en": "eminent, distinguished",
     "pos": "adj.",
     "example": {
      "target": "C'est un éminent spécialiste de la question.",
      "gloss": "He is an eminent specialist on the subject."
     }
    },
    {
     "id": "illustre",
     "hr": "illustre",
     "en": "illustrious",
     "pos": "adj.",
     "example": {
      "target": "Il descend, dit-on, d'une illustre famille.",
      "gloss": "He is said to descend from an illustrious family."
     }
    },
    {
     "id": "patent",
     "hr": "patent",
     "en": "patent, obvious",
     "pos": "adj.",
     "note": "f. patente",
     "example": {
      "target": "Il y a là une injustice patente.",
      "gloss": "There is a patent injustice here."
     }
    },
    {
     "id": "criant",
     "hr": "criant",
     "en": "glaring, blatant",
     "pos": "adj.",
     "example": {
      "target": "Cette disparité est d'une injustice criante.",
      "gloss": "This disparity is a glaring injustice."
     }
    },
    {
     "id": "édifiant",
     "hr": "édifiant",
     "en": "revealing, instructive",
     "pos": "adj.",
     "example": {
      "target": "Le rapport est édifiant sur les dérives du secteur.",
      "gloss": "The report is revealing about the sector's excesses."
     }
    },
    {
     "id": "affligeant",
     "hr": "affligeant",
     "en": "distressing, pitiful",
     "pos": "adj.",
     "example": {
      "target": "Le niveau du débat était tout simplement affligeant.",
      "gloss": "The level of the debate was simply pitiful."
     }
    },
    {
     "id": "consternant",
     "hr": "consternant",
     "en": "appalling, dismaying",
     "pos": "adj.",
     "example": {
      "target": "Une telle légèreté est consternante.",
      "gloss": "Such carelessness is appalling."
     }
    },
    {
     "id": "déplorable",
     "hr": "déplorable",
     "en": "deplorable, dreadful",
     "pos": "adj.",
     "example": {
      "target": "L'affaire a été gérée de façon déplorable.",
      "gloss": "The matter was handled deplorably."
     }
    },
    {
     "id": "exécrable",
     "hr": "exécrable",
     "en": "atrocious, foul",
     "pos": "adj.",
     "example": {
      "target": "Le service était d'une lenteur exécrable.",
      "gloss": "The service was atrociously slow."
     }
    },
    {
     "id": "fâcheux",
     "hr": "fâcheux",
     "en": "unfortunate, regrettable",
     "pos": "adj.",
     "note": "f. fâcheuse",
     "example": {
      "target": "Cette maladresse a eu de fâcheuses conséquences.",
      "gloss": "This blunder had unfortunate consequences."
     }
    },
    {
     "id": "fastidieux",
     "hr": "fastidieux",
     "en": "tedious",
     "pos": "adj.",
     "note": "f. fastidieuse",
     "example": {
      "target": "La vérification, aussi fastidieuse soit-elle, est indispensable.",
      "gloss": "The checking, tedious as it is, is essential."
     }
    },
    {
     "id": "rébarbatif",
     "hr": "rébarbatif",
     "en": "off-putting, forbidding",
     "pos": "adj.",
     "note": "f. rébarbative",
     "example": {
      "target": "Le sujet paraît rébarbatif mais se révèle passionnant.",
      "gloss": "The subject seems forbidding but turns out to be fascinating."
     }
    },
    {
     "id": "ardu",
     "hr": "ardu",
     "en": "arduous, difficult",
     "pos": "adj.",
     "note": "f. ardue",
     "example": {
      "target": "La démonstration est ardue mais parfaitement rigoureuse.",
      "gloss": "The proof is arduous but perfectly rigorous."
     }
    },
    {
     "id": "épineux",
     "hr": "épineux",
     "en": "thorny, tricky",
     "pos": "adj.",
     "note": "f. épineuse",
     "example": {
      "target": "Nous abordons ici une question épineuse.",
      "gloss": "We now come to a thorny question."
     }
    },
    {
     "id": "laborieux",
     "hr": "laborieux",
     "en": "laborious, painstaking",
     "pos": "adj.",
     "note": "f. laborieuse",
     "example": {
      "target": "Il est parvenu au résultat au prix d'un travail laborieux.",
      "gloss": "He reached the result through painstaking work."
     }
    },
    {
     "id": "ténu",
     "hr": "ténu",
     "en": "tenuous, slight",
     "pos": "adj.",
     "note": "f. ténue",
     "example": {
      "target": "Le lien entre les deux faits reste bien ténu.",
      "gloss": "The link between the two facts remains very tenuous."
     }
    },
    {
     "id": "limpide",
     "hr": "limpide",
     "en": "crystal-clear, limpid",
     "pos": "adj.",
     "example": {
      "target": "Sa démonstration est d'une clarté limpide.",
      "gloss": "His demonstration is crystal-clear."
     }
    },
    {
     "id": "éloquent",
     "hr": "éloquent",
     "en": "eloquent, telling",
     "pos": "adj.",
     "example": {
      "target": "Les chiffres sont, à cet égard, éloquents.",
      "gloss": "The figures are, in this respect, telling."
     }
    },
    {
     "id": "captieux",
     "hr": "captieux",
     "en": "specious, misleading",
     "pos": "adj.",
     "note": "f. captieuse",
     "example": {
      "target": "Cet argument captieux séduit d'abord, puis déçoit.",
      "gloss": "This specious argument first seduces, then disappoints."
     }
    },
    {
     "id": "oiseux",
     "hr": "oiseux",
     "en": "idle, pointless",
     "pos": "adj.",
     "note": "f. oiseuse",
     "example": {
      "target": "Épargnons-nous ces débats oiseux.",
      "gloss": "Let us spare ourselves these idle debates."
     }
    },
    {
     "id": "lapidaire",
     "hr": "lapidaire",
     "en": "terse, laconic",
     "pos": "adj.",
     "example": {
      "target": "Il a résumé l'affaire d'une formule lapidaire.",
      "gloss": "He summed up the matter in a terse phrase."
     }
    },
    {
     "id": "laconique",
     "hr": "laconique",
     "en": "laconic, terse",
     "pos": "adj.",
     "example": {
      "target": "Sa réponse laconique en disait long.",
      "gloss": "His laconic reply spoke volumes."
     }
    },
    {
     "id": "prolixe",
     "hr": "prolixe",
     "en": "long-winded, prolix",
     "pos": "adj.",
     "example": {
      "target": "L'auteur, souvent prolixe, se fait ici concis.",
      "gloss": "The author, often long-winded, is concise here."
     }
    },
    {
     "id": "succinct",
     "hr": "succinct",
     "en": "succinct, brief",
     "pos": "adj.",
     "note": "f. succincte",
     "example": {
      "target": "Un exposé succinct suffira à éclairer le lecteur.",
      "gloss": "A brief account will suffice to inform the reader."
     }
    },
    {
     "id": "concis",
     "hr": "concis",
     "en": "concise",
     "pos": "adj.",
     "note": "f. concise",
     "example": {
      "target": "Son style, concis et net, va droit au but.",
      "gloss": "His style, concise and crisp, goes straight to the point."
     }
    },
    {
     "id": "lacunaire",
     "hr": "lacunaire",
     "en": "incomplete, patchy",
     "pos": "adj.",
     "example": {
      "target": "Nos connaissances restent lacunaires sur ce point.",
      "gloss": "Our knowledge remains patchy on this point."
     }
    },
    {
     "id": "acuité",
     "hr": "acuité",
     "en": "acuteness, sharpness",
     "pos": "n. f.",
     "example": {
      "target": "Il analyse la société avec une rare acuité.",
      "gloss": "He analyses society with rare acuteness."
     }
    },
    {
     "id": "célérité",
     "hr": "célérité",
     "en": "swiftness, celerity",
     "pos": "n. f.",
     "example": {
      "target": "L'affaire a été traitée avec une célérité surprenante.",
      "gloss": "The matter was dealt with surprising swiftness."
     }
    },
    {
     "id": "longévité",
     "hr": "longévité",
     "en": "longevity",
     "pos": "n. f.",
     "example": {
      "target": "La longévité de ce régime tient à sa capacité d'adaptation.",
      "gloss": "The longevity of this regime lies in its ability to adapt."
     }
    },
    {
     "id": "véracité",
     "hr": "véracité",
     "en": "truthfulness, veracity",
     "pos": "n. f.",
     "example": {
      "target": "Rien ne permet de mettre en doute la véracité du récit.",
      "gloss": "Nothing allows the truthfulness of the account to be doubted."
     }
    },
    {
     "id": "authenticité",
     "hr": "authenticité",
     "en": "authenticity",
     "pos": "n. f.",
     "example": {
      "target": "Les experts ont confirmé l'authenticité du document.",
      "gloss": "Experts confirmed the authenticity of the document."
     }
    },
    {
     "id": "futilité",
     "hr": "futilité",
     "en": "futility, triviality",
     "pos": "n. f.",
     "example": {
      "target": "Il se perd dans la futilité des mondanités.",
      "gloss": "He loses himself in the triviality of social life."
     }
    },
    {
     "id": "banalité",
     "hr": "banalité",
     "en": "banality, triteness",
     "pos": "n. f.",
     "example": {
      "target": "Le discours enchaînait les banalités.",
      "gloss": "The speech strung together one platitude after another."
     }
    },
    {
     "id": "vacuité",
     "hr": "vacuité",
     "en": "emptiness, vacuity",
     "pos": "n. f.",
     "example": {
      "target": "Derrière ces grands mots, quelle vacuité !",
      "gloss": "Behind these grand words, what emptiness!"
     }
    },
    {
     "id": "opacité",
     "hr": "opacité",
     "en": "opacity, obscurity",
     "pos": "n. f.",
     "example": {
      "target": "On dénonce l'opacité des circuits de financement.",
      "gloss": "The opacity of the funding channels is denounced."
     }
    },
    {
     "id": "unanimité",
     "hr": "unanimité",
     "en": "unanimity",
     "pos": "n. f.",
     "example": {
      "target": "La motion a été adoptée à l'unanimité.",
      "gloss": "The motion was adopted unanimously."
     }
    },
    {
     "id": "notoriété",
     "hr": "notoriété",
     "en": "renown, fame",
     "pos": "n. f.",
     "example": {
      "target": "Sa notoriété a depuis largement dépassé les frontières.",
      "gloss": "His renown has since spread well beyond the borders."
     }
    },
    {
     "id": "postérité",
     "hr": "postérité",
     "en": "posterity",
     "pos": "n. f.",
     "example": {
      "target": "L'histoire jugera ; la postérité tranchera.",
      "gloss": "History will judge; posterity will decide."
     }
    },
    {
     "id": "prospérité",
     "hr": "prospérité",
     "en": "prosperity",
     "pos": "n. f.",
     "example": {
      "target": "Le pays connut alors une longue prospérité.",
      "gloss": "The country then enjoyed a long prosperity."
     }
    },
    {
     "id": "adversité",
     "hr": "adversité",
     "en": "adversity",
     "pos": "n. f.",
     "example": {
      "target": "On juge un homme à sa tenue dans l'adversité.",
      "gloss": "A man is judged by his conduct in adversity."
     }
    },
    {
     "id": "crédulité",
     "hr": "crédulité",
     "en": "credulity, gullibility",
     "pos": "n. f.",
     "example": {
      "target": "Ces escrocs exploitent la crédulité du public.",
      "gloss": "These crooks exploit the public's credulity."
     }
    },
    {
     "id": "dogmatisme",
     "hr": "dogmatisme",
     "en": "dogmatism",
     "pos": "n. m.",
     "example": {
      "target": "Son dogmatisme l'empêche d'entendre la contradiction.",
      "gloss": "His dogmatism prevents him from hearing dissent."
     }
    },
    {
     "id": "conformisme",
     "hr": "conformisme",
     "en": "conformism",
     "pos": "n. m.",
     "example": {
      "target": "Il faut un certain courage pour braver le conformisme ambiant.",
      "gloss": "It takes some courage to defy the prevailing conformism."
     }
    },
    {
     "id": "opportunisme",
     "hr": "opportunisme",
     "en": "opportunism",
     "pos": "n. m.",
     "example": {
      "target": "On lui reproche un opportunisme sans scrupules.",
      "gloss": "He is criticised for unscrupulous opportunism."
     }
    },
    {
     "id": "cynisme",
     "hr": "cynisme",
     "en": "cynicism",
     "pos": "n. m.",
     "example": {
      "target": "Il affiche un cynisme qui glace ses interlocuteurs.",
      "gloss": "He displays a cynicism that chills those he talks to."
     }
    },
    {
     "id": "fatalisme",
     "hr": "fatalisme",
     "en": "fatalism",
     "pos": "n. m.",
     "example": {
      "target": "Ce fatalisme ambiant décourage toute action.",
      "gloss": "This prevailing fatalism discourages any action."
     }
    },
    {
     "id": "idéalisme",
     "hr": "idéalisme",
     "en": "idealism",
     "pos": "n. m.",
     "example": {
      "target": "Son idéalisme se heurte vite au principe de réalité.",
      "gloss": "His idealism soon collides with the reality principle."
     }
    },
    {
     "id": "pragmatisme",
     "hr": "pragmatisme",
     "en": "pragmatism",
     "pos": "n. m.",
     "example": {
      "target": "Le pragmatisme l'emporte souvent sur les principes.",
      "gloss": "Pragmatism often prevails over principles."
     }
    },
    {
     "id": "élitisme",
     "hr": "élitisme",
     "en": "elitism",
     "pos": "n. m.",
     "example": {
      "target": "On reproche à cette institution son élitisme.",
      "gloss": "This institution is criticised for its elitism."
     }
    },
    {
     "id": "obscurantisme",
     "hr": "obscurantisme",
     "en": "obscurantism",
     "pos": "n. m.",
     "example": {
      "target": "La science a longtemps dû lutter contre l'obscurantisme.",
      "gloss": "Science long had to fight against obscurantism."
     }
    },
    {
     "id": "laxisme",
     "hr": "laxisme",
     "en": "laxity, permissiveness",
     "pos": "n. m.",
     "example": {
      "target": "On dénonce tantôt le laxisme, tantôt la sévérité.",
      "gloss": "Laxity is denounced at times, severity at others."
     }
    },
    {
     "id": "défiance",
     "hr": "défiance",
     "en": "distrust, wariness",
     "pos": "n. f.",
     "example": {
      "target": "Une profonde défiance s'est installée envers les institutions.",
      "gloss": "A deep distrust of institutions has set in."
     }
    },
    {
     "id": "bienséance",
     "hr": "bienséance",
     "en": "propriety, decorum",
     "pos": "n. f.",
     "example": {
      "target": "Il a franchi les limites de la bienséance.",
      "gloss": "He overstepped the bounds of propriety."
     }
    },
    {
     "id": "prévenance",
     "hr": "prévenance",
     "en": "thoughtfulness, considerateness",
     "pos": "n. f.",
     "example": {
      "target": "Il entoure ses hôtes de mille prévenances.",
      "gloss": "He surrounds his guests with countless considerate attentions."
     }
    },
    {
     "id": "connivence",
     "hr": "connivence",
     "en": "complicity, connivance",
     "pos": "n. f.",
     "example": {
      "target": "Ils échangèrent un regard de connivence.",
      "gloss": "They exchanged a knowing look of complicity."
     }
    },
    {
     "id": "outrance",
     "hr": "outrance",
     "en": "excess, extremeness",
     "pos": "n. f.",
     "note": "à outrance : to excess",
     "example": {
      "target": "Le débat sombre parfois dans l'outrance.",
      "gloss": "The debate sometimes descends into excess."
     }
    },
    {
     "id": "recrudescence",
     "hr": "recrudescence",
     "en": "resurgence, upsurge",
     "pos": "n. f.",
     "example": {
      "target": "On observe une recrudescence des incivilités.",
      "gloss": "An upsurge in antisocial behaviour is observed."
     }
    },
    {
     "id": "effervescence",
     "hr": "effervescence",
     "en": "ferment, buzz",
     "pos": "n. f.",
     "example": {
      "target": "La ville est en pleine effervescence culturelle.",
      "gloss": "The city is in a state of cultural ferment."
     }
    },
    {
     "id": "dissonance",
     "hr": "dissonance",
     "en": "dissonance, discord",
     "pos": "n. f.",
     "example": {
      "target": "Il y a une dissonance entre le ton et le propos.",
      "gloss": "There is a dissonance between the tone and the content."
     }
    },
    {
     "id": "résonance",
     "hr": "résonance",
     "en": "resonance",
     "pos": "n. f.",
     "example": {
      "target": "Ce texte ancien garde une étrange résonance aujourd'hui.",
      "gloss": "This old text retains a strange resonance today."
     }
    },
    {
     "id": "redondance",
     "hr": "redondance",
     "en": "redundancy, repetition",
     "pos": "n. f.",
     "example": {
      "target": "On éliminera les redondances inutiles du texte.",
      "gloss": "Needless repetitions will be removed from the text."
     }
    },
    {
     "id": "solitude",
     "hr": "solitude",
     "en": "solitude, loneliness",
     "pos": "n. f.",
     "example": {
      "target": "Il a fini par apprivoiser sa solitude.",
      "gloss": "He eventually came to terms with his solitude."
     }
    },
    {
     "id": "plénitude",
     "hr": "plénitude",
     "en": "fullness, plenitude",
     "pos": "n. f.",
     "example": {
      "target": "Il exerce désormais ses fonctions en toute plénitude.",
      "gloss": "He now exercises his duties in full."
     }
    },
    {
     "id": "latitude",
     "hr": "latitude",
     "en": "leeway, latitude",
     "pos": "n. f.",
     "example": {
      "target": "On lui laisse toute latitude pour mener le projet.",
      "gloss": "He is given full latitude to run the project."
     }
    },
    {
     "id": "désuétude",
     "hr": "désuétude",
     "en": "obsolescence, disuse",
     "pos": "n. f.",
     "note": "tomber en désuétude",
     "example": {
      "target": "Cette loi est tombée en désuétude.",
      "gloss": "This law has fallen into disuse."
     }
    },
    {
     "id": "rectitude",
     "hr": "rectitude",
     "en": "rectitude, straightness",
     "pos": "n. f.",
     "example": {
      "target": "On admire chez lui une rectitude morale sans faille.",
      "gloss": "One admires in him an unfailing moral rectitude."
     }
    },
    {
     "id": "béatitude",
     "hr": "béatitude",
     "en": "bliss, beatitude",
     "pos": "n. f.",
     "example": {
      "target": "Il souriait dans une parfaite béatitude.",
      "gloss": "He was smiling in perfect bliss."
     }
    },
    {
     "id": "promptitude",
     "hr": "promptitude",
     "en": "promptness, swiftness",
     "pos": "n. f.",
     "example": {
      "target": "Il a réagi avec une promptitude remarquable.",
      "gloss": "He reacted with remarkable promptness."
     }
    },
    {
     "id": "servilité",
     "hr": "servilité",
     "en": "servility",
     "pos": "n. f.",
     "example": {
      "target": "Sa servilité envers ses supérieurs finit par lasser.",
      "gloss": "His servility towards his superiors eventually wears thin."
     }
    },
    {
     "id": "docilité",
     "hr": "docilité",
     "en": "docility, compliance",
     "pos": "n. f.",
     "example": {
      "target": "On attend de lui non de la docilité, mais du jugement.",
      "gloss": "What is expected of him is not docility but judgement."
     }
    },
    {
     "id": "acrimonie",
     "hr": "acrimonie",
     "en": "acrimony, bitterness",
     "pos": "n. f.",
     "example": {
      "target": "Ils ont débattu longtemps, mais sans acrimonie.",
      "gloss": "They debated at length, but without acrimony."
     }
    },
    {
     "id": "truculence",
     "hr": "truculence",
     "en": "colourfulness, earthiness",
     "pos": "n. f.",
     "example": {
      "target": "Le récit est raconté avec une savoureuse truculence.",
      "gloss": "The tale is told with delicious earthiness."
     }
    },
    {
     "id": "mièvrerie",
     "hr": "mièvrerie",
     "en": "mawkishness, sappiness",
     "pos": "n. f.",
     "example": {
      "target": "Le film verse parfois dans la mièvrerie.",
      "gloss": "The film sometimes lapses into mawkishness."
     }
    },
    {
     "id": "magnanimité",
     "hr": "magnanimité",
     "en": "magnanimity",
     "pos": "n. f.",
     "example": {
      "target": "Le vainqueur a fait preuve d'une rare magnanimité.",
      "gloss": "The victor showed rare magnanimity."
     }
    },
    {
     "id": "pusillanimité",
     "hr": "pusillanimité",
     "en": "pusillanimity, faint-heartedness",
     "pos": "n. f.",
     "example": {
      "target": "Sa pusillanimité l'a empêché de saisir sa chance.",
      "gloss": "His faint-heartedness stopped him from seizing his chance."
     }
    },
    {
     "id": "pugnacité",
     "hr": "pugnacité",
     "en": "pugnacity, combativeness",
     "pos": "n. f.",
     "example": {
      "target": "Elle défend ses dossiers avec une pugnacité redoutable.",
      "gloss": "She defends her cases with formidable combativeness."
     }
    }
   ]
  }
 ]
}
